gena/__init__.py
gena/api_generator.py
gena/api_testsuite.py
gena/app_generator.py
gena/client.py
gena/config.py
gena/custom_fields.py
gena/deserializer.py
gena/serializer.py
gena-1.7.1.dist-info/LICENSE
gena-1.7.1.dist-info/METADATA
gena-1.7.1.dist-info/WHEEL
gena-1.7.1.dist-info/RECORD
